LICENSE
README.rst
setup.py
testflows.github.hetzner.runners.egg-info/PKG-INFO
testflows.github.hetzner.runners.egg-info/SOURCES.txt
testflows.github.hetzner.runners.egg-info/dependency_links.txt
testflows.github.hetzner.runners.egg-info/not-zip-safe
testflows.github.hetzner.runners.egg-info/requires.txt
testflows.github.hetzner.runners.egg-info/top_level.txt
testflows/github/hetzner/runners/__init__.py
testflows/github/hetzner/runners/actions.py
testflows/github/hetzner/runners/api_watch.py
testflows/github/hetzner/runners/args.py
testflows/github/hetzner/runners/cloud.py
testflows/github/hetzner/runners/constants.py
testflows/github/hetzner/runners/estimate.py
testflows/github/hetzner/runners/hclient.py
testflows/github/hetzner/runners/images.py
testflows/github/hetzner/runners/logger.py
testflows/github/hetzner/runners/metrics.py
testflows/github/hetzner/runners/ordered_set.py
testflows/github/hetzner/runners/projects.py
testflows/github/hetzner/runners/request.py
testflows/github/hetzner/runners/scale_down.py
testflows/github/hetzner/runners/scale_up.py
testflows/github/hetzner/runners/server.py
testflows/github/hetzner/runners/servers.py
testflows/github/hetzner/runners/service.py
testflows/github/hetzner/runners/shell.py
testflows/github/hetzner/runners/streamingyaml.py
testflows/github/hetzner/runners/utils.py
testflows/github/hetzner/runners/volumes.py
testflows/github/hetzner/runners/bin/github-hetzner-runners
testflows/github/hetzner/runners/config/__init__.py
testflows/github/hetzner/runners/config/config.py
testflows/github/hetzner/runners/config/schema.json
testflows/github/hetzner/runners/dashboard/__init__.py
testflows/github/hetzner/runners/dashboard/bootstrap.py
testflows/github/hetzner/runners/dashboard/chart.py
testflows/github/hetzner/runners/dashboard/colors.py
testflows/github/hetzner/runners/dashboard/dashboard.py
testflows/github/hetzner/runners/dashboard/format.py
testflows/github/hetzner/runners/dashboard/renderers.py
testflows/github/hetzner/runners/dashboard/metrics/__init__.py
testflows/github/hetzner/runners/dashboard/metrics/cost.py
testflows/github/hetzner/runners/dashboard/metrics/errors.py
testflows/github/hetzner/runners/dashboard/metrics/get.py
testflows/github/hetzner/runners/dashboard/metrics/heartbeat.py
