Metadata-Version: 2.1
Name: testflows.github.hetzner.runners
Version: 1.10.250911.1235809
Summary: Autoscaling GitHub Actions Runners Using Hetzner Cloud 
Home-page: https://github.com/testflows/testflows-github-hetzner-runners
Author: Vitaliy Zakaznikov
Author-email: vzakaznikov@testflows.com
License: Apache-2.0
Classifier: Development Status :: 4 - Beta
Classifier: Programming Language :: Python :: 3
Classifier: License :: OSI Approved :: Apache Software License
Classifier: Operating System :: POSIX :: Linux
Requires-Python: >=3.8
License-File: LICENSE
Requires-Dist: PyGithub==1.59.0
Requires-Dist: hcloud==2.3.0
Requires-Dist: requests-cache==1.1.0
Requires-Dist: PyYAML==6.0.2
Requires-Dist: prometheus_client==0.19.0
Requires-Dist: streamlit==1.49.1
Requires-Dist: psutil>=5.9.8
Provides-Extra: dev
